Metadata-Version: 1.0
Name: gau-bin-probability-33
Version: 0.1
Summary: Gaussian and Binomial distributions
Home-page: UNKNOWN
Author: Ilhwan Park
Author-email: ihp111@gmail.com
License: UNKNOWN
Platform: UNKNOWN
